torchestra/__init__.py
torchestra/_debugging.py
torchestra/_lookups.py
torchestra/_normalization.py
torchestra/_pipes.py
torchestra/_sparse_slices.py
torchestra/_stats_plan.py
torchestra/_wrappers.py
torchestra/py.typed
torchestra/test_debugging.py
torchestra/test_lookups.py
torchestra/test_normalization.py
torchestra/test_pipes.py
torchestra/test_sparse_slices.py
torchestra/test_stats_plan.py
torchestra/test_wrappers.py
torchestra-0.1.7.dist-info/METADATA
torchestra-0.1.7.dist-info/WHEEL
torchestra-0.1.7.dist-info/licenses/LICENSE.md
torchestra-0.1.7.dist-info/RECORD
