Metadata-Version: 2.4
Name: torchestra
Version: 0.1.7
Project-URL: Homepage, https://github.com/jussi-kalliokoski/torchestra
Project-URL: Bug Tracker, https://github.com/jussi-kalliokoski/torchestra/issues
Author-email: Jussi Kalliokoski <jussi.kalliokoski@gmail.com>
License: MIT License
License-File: LICENSE.md
Keywords: feature,preprocessing,pytorch,ray,torch,torchscript,typing
Classifier: License :: OSI Approved :: MIT License
Classifier: Operating System :: OS Independent
Classifier: Programming Language :: Python :: 3
Requires-Python: >=3.10.12
Requires-Dist: torch>=2.2.2
